{
    "id": "448863996905521162",
    "name": "Test Dream.Os",
    "clan": "Uchiha",
    "level": 60,
    "rank": "Genin",
    "hp": 800,
    "max_hp": 800,
    "chakra": 600,
    "max_chakra": 600,
    "stamina": 400,
    "max_stamina": 400,
    "strength": 45,
    "defense": 40,
    "speed": 42,
    "ninjutsu": 50,
    "genjutsu": 45,
    "taijutsu": 48,
    "wins": 0,
    "losses": 0,
    "draws": 0,
    "wins_against_rank": {},
    "exp": 0,
    "specialization": null,
    "willpower": 35,
    "chakra_control": 40,
    "intelligence": 38,
    "perception": 35,
    "jutsu": [
        "Fireball Jutsu",
        "Great Fireball Jutsu",
        "Phoenix Sage Fire",
        "Dragon Flame Jutsu",
        "Shadow Clone Jutsu",
        "Rasengan",
        "Chidori",
        "Substitution Jutsu"
    ],
    "equipment": {},
    "inventory": [],
    "is_active": true,
    "status_effects": [],
    "active_effects": {},
    "status_conditions": {},
    "buffs": {},
    "debuffs": {},
    "achievements": [
        "First Battle Won",
        "Defeated 10 Opponents",
        "Defeated 50 Opponents",
        "Elite Warrior",
        "Jutsu Master"
    ],
    "titles": [],
    "completed_missions": [],
    "jutsu_mastery": {},
    "last_daily_claim": null,
    "active_mission_id": null
}